client/__init__.py
client/client.py
client/clientstorage.py
client/login_window.py
client/main_window.py
client/common/__init__.py
client/common/utils.py
client/common/variables.py
messenger_client_serg-0.0.1.dist-info/METADATA
messenger_client_serg-0.0.1.dist-info/WHEEL
messenger_client_serg-0.0.1.dist-info/top_level.txt
messenger_client_serg-0.0.1.dist-info/RECORD
